betwatch/__about__.py
betwatch/__init__.py
betwatch/client.py
betwatch/client_async.py
betwatch/exceptions.py
betwatch/queries.py
betwatch/types/__init__.py
betwatch/types/bookmakers.py
betwatch/types/exceptions.py
betwatch/types/filters.py
betwatch/types/markets.py
betwatch/types/race.py
betwatch/types/updates.py
betwatch-1.6.0.dist-info/METADATA
betwatch-1.6.0.dist-info/WHEEL
betwatch-1.6.0.dist-info/licenses/LICENSE.txt
betwatch-1.6.0.dist-info/RECORD
