Metadata-Version: 2.4
Name: betwatch
Version: 1.6.0
Summary: A Python package for interacting with the Betwatch.com API
Project-URL: Documentation, https://github.com/betwatch/betwatch-sdk-python#readme
Project-URL: Issues, https://github.com/betwatch/betwatch-sdk-python/issues
Project-URL: Source, https://github.com/betwatch/betwatch-sdk-python
Project-URL: Betwatch.com, https://betwatch.com
Author-email: Jamie Watts <jamie@betwatch.com>
License-Expression: MIT
License-File: LICENSE.txt
Keywords: api,betting,betwatch,sdk,sports
Classifier: Development Status :: 4 - Beta
Classifier: Programming Language :: Python
Classifier: Programming Language :: Python :: 3.10
Classifier: Programming Language :: Python :: 3.11
Classifier: Programming Language :: Python :: 3.12
Classifier: Programming Language :: Python :: Implementation :: CPython
Classifier: Programming Language :: Python :: Implementation :: PyPy
Requires-Python: >=3.10
Requires-Dist: ciso8601>=2.3.3
Requires-Dist: gql[httpx,requests,websockets]>=4.0.0
Requires-Dist: typedload>=2.39
